skprune/__init__.py
scikit_prune-0.1.0.dist-info/LICENSE
scikit_prune-0.1.0.dist-info/METADATA
scikit_prune-0.1.0.dist-info/WHEEL
scikit_prune-0.1.0.dist-info/top_level.txt
scikit_prune-0.1.0.dist-info/RECORD
