Metadata-Version: 2.1
Name: scikit-prune
Version: 0.1.0
Summary: Prune your sklearn models.
Home-page: https://github.com/koaning/scikit-prune
Author: Vincent D. Warmerdam
Classifier: Intended Audience :: Developers
Classifier: Intended Audience :: Science/Research
Classifier: Programming Language :: Python :: 3
Classifier: Programming Language :: Python :: 3.8
Classifier: Programming Language :: Python :: 3.9
Classifier: Programming Language :: Python :: 3.10
Classifier: Programming Language :: Python :: 3.11
Classifier: License :: OSI Approved :: MIT License
Classifier: Topic :: Scientific/Engineering
Classifier: Topic :: Scientific/Engineering :: Artificial Intelligence
License-File: LICENSE
Requires-Dist: scikit-learn (>=1.0.0)
